share.py
share_cli-0.4.7.dist-info/licenses/LICENSE
share_cli-0.4.7.dist-info/METADATA
share_cli-0.4.7.dist-info/WHEEL
share_cli-0.4.7.dist-info/entry_points.txt
share_cli-0.4.7.dist-info/top_level.txt
share_cli-0.4.7.dist-info/RECORD
