Metadata-Version: 2.4
Name: share-cli
Version: 0.4.7
Summary: A simple file server
Author-email: Jackie Han <jackiehank@163.com>
License: The MIT License (MIT)
Project-URL: Homepage, https://github.com/jackiehank/share
Requires-Python: >=3.8
License-File: LICENSE
Provides-Extra: dev
Requires-Dist: pytest>=8.4.2; extra == "dev"
Requires-Dist: requests>=2.32.5; extra == "dev"
Requires-Dist: ruff>=0.12.12; extra == "dev"
Dynamic: license-file
